{
  "datasets": [
    {
      "name": "b506e8bb",
      "displayName": "vw_fact_orders_enriched",
      "queryLines": [
        "SELECT * FROM fmcg.gold.vw_fact_orders_enriched"
      ]
    }
  ],
  "pages": [
    {
      "name": "34e0e054",
      "displayName": "Sales",
      "layout": [
        {
          "widget": {
            "name": "9d77e924",
            "multilineTextboxSpec": {
              "lines": [
                "<p>&nbsp;</p>\n",
                "\n",
                "<span style=\"font-size:32px\">**Sales Insights**</span>"
              ]
            }
          },
          "position": {
            "x": 0,
            "y": 0,
            "width": 12,
            "height": 2
          }
        },
        {
          "widget": {
            "name": "category",
            "queries": [
              {
                "name": "dashboards/01f1094cd13117499b59fa40d43f5a5a/datasets/01f1094dccbb1206b4a0872f3df23ee8_category",
                "query": {
                  "datasetName": "b506e8bb",
                  "fields": [
                    {
                      "name": "category",
                      "expression": "`category`"
                    },
                    {
                      "name": "category_associativity",
                      "expression": "COUNT_IF(`associative_filter_predicate_group`)"
                    }
                  ],
                  "disaggregated": false
                }
              }
            ],
            "spec": {
              "version": 2,
              "frame": {
                "showTitle": true,
                "showDescription": true,
                "description": "",
                "title": "Category"
              },
              "widgetType": "filter-single-select",
              "encodings": {
                "fields": [
                  {
                    "fieldName": "category",
                    "queryName": "dashboards/01f1094cd13117499b59fa40d43f5a5a/datasets/01f1094dccbb1206b4a0872f3df23ee8_category"
                  }
                ]
              }
            }
          },
          "position": {
            "x": 0,
            "y": 2,
            "width": 3,
            "height": 1
          }
        },
        {
          "widget": {
            "name": "year",
            "queries": [
              {
                "name": "dashboards/01f1094cd13117499b59fa40d43f5a5a/datasets/01f1094dccbb1206b4a0872f3df23ee8_year",
                "query": {
                  "datasetName": "b506e8bb",
                  "fields": [
                    {
                      "name": "year",
                      "expression": "`year`"
                    },
                    {
                      "name": "year_associativity",
                      "expression": "COUNT_IF(`associative_filter_predicate_group`)"
                    }
                  ],
                  "disaggregated": false
                }
              }
            ],
            "spec": {
              "version": 2,
              "frame": {
                "showTitle": true,
                "title": "Year"
              },
              "widgetType": "filter-single-select",
              "encodings": {
                "fields": [
                  {
                    "fieldName": "year",
                    "queryName": "dashboards/01f1094cd13117499b59fa40d43f5a5a/datasets/01f1094dccbb1206b4a0872f3df23ee8_year"
                  }
                ]
              }
            }
          },
          "position": {
            "x": 3,
            "y": 2,
            "width": 3,
            "height": 1
          }
        },
        {
          "widget": {
            "name": "18c63afe",
            "queries": [
              {
                "name": "main_query",
                "query": {
                  "datasetName": "b506e8bb",
                  "fields": [
                    {
                      "name": "month_short_name",
                      "expression": "`month_short_name`"
                    },
                    {
                      "name": "sum(total_amount_inr)",
                      "expression": "SUM(`total_amount_inr`)"
                    }
                  ],
                  "disaggregated": false
                }
              }
            ],
            "spec": {
              "version": 3,
              "frame": {
                "showTitle": false,
                "showDescription": false
              },
              "mark": {
                "colors": [
                  {
                    "themeColorType": "visualizationColors",
                    "position": 10
                  },
                  {
                    "themeColorType": "visualizationColors",
                    "position": 2
                  },
                  {
                    "themeColorType": "visualizationColors",
                    "position": 3
                  },
                  {
                    "themeColorType": "visualizationColors",
                    "position": 4
                  },
                  {
                    "themeColorType": "visualizationColors",
                    "position": 5
                  },
                  {
                    "themeColorType": "visualizationColors",
                    "position": 6
                  },
                  {
                    "themeColorType": "visualizationColors",
                    "position": 7
                  },
                  {
                    "themeColorType": "visualizationColors",
                    "position": 8
                  },
                  {
                    "themeColorType": "visualizationColors",
                    "position": 9
                  },
                  {
                    "themeColorType": "visualizationColors",
                    "position": 10
                  }
                ]
              },
              "widgetType": "bar",
              "encodings": {
                "x": {
                  "fieldName": "month_short_name",
                  "scale": {
                    "type": "categorical"
                  }
                },
                "y": {
                  "fieldName": "sum(total_amount_inr)",
                  "scale": {
                    "type": "quantitative"
                  }
                },
                "label": {
                  "show": false
                }
              }
            }
          },
          "position": {
            "x": 0,
            "y": 3,
            "width": 6,
            "height": 6
          }
        },
        {
          "widget": {
            "name": "month_name",
            "queries": [
              {
                "name": "dashboards/01f1094cd13117499b59fa40d43f5a5a/datasets/01f1094dccbb1206b4a0872f3df23ee8_month_name",
                "query": {
                  "datasetName": "b506e8bb",
                  "fields": [
                    {
                      "name": "month_name",
                      "expression": "`month_name`"
                    },
                    {
                      "name": "month_name_associativity",
                      "expression": "COUNT_IF(`associative_filter_predicate_group`)"
                    }
                  ],
                  "disaggregated": false
                }
              }
            ],
            "spec": {
              "version": 2,
              "frame": {
                "showTitle": true,
                "title": "Month_name"
              },
              "widgetType": "filter-single-select",
              "encodings": {
                "fields": [
                  {
                    "fieldName": "month_name",
                    "queryName": "dashboards/01f1094cd13117499b59fa40d43f5a5a/datasets/01f1094dccbb1206b4a0872f3df23ee8_month_name"
                  }
                ]
              }
            }
          },
          "position": {
            "x": 6,
            "y": 2,
            "width": 3,
            "height": 1
          }
        },
        {
          "widget": {
            "name": "0653cf28",
            "queries": [
              {
                "name": "main_query",
                "query": {
                  "datasetName": "b506e8bb",
                  "fields": [
                    {
                      "name": "sum(sold_quantity)",
                      "expression": "SUM(`sold_quantity`)"
                    },
                    {
                      "name": "quarter",
                      "expression": "`quarter`"
                    }
                  ],
                  "disaggregated": false
                }
              }
            ],
            "spec": {
              "version": 3,
              "frame": {
                "title": "Sold Quantity by Quarter",
                "showTitle": true
              },
              "widgetType": "pie",
              "encodings": {
                "angle": {
                  "fieldName": "sum(sold_quantity)",
                  "scale": {
                    "type": "quantitative"
                  },
                  "displayName": "Sold Quantity"
                },
                "color": {
                  "fieldName": "quarter",
                  "legend": {
                    "position": "top"
                  },
                  "displayName": "Quarter",
                  "scale": {
                    "type": "categorical",
                    "mappings": [
                      {
                        "value": "Q4",
                        "color": {
                          "themeColorType": "visualizationColors",
                          "position": 8
                        }
                      },
                      {
                        "value": "Q2",
                        "color": "#E2557A"
                      },
                      {
                        "value": "Q1",
                        "color": {
                          "themeColorType": "canvasBackgroundColor"
                        }
                      },
                      {
                        "value": "Q3",
                        "color": {
                          "themeColorType": "visualizationColors",
                          "position": 9
                        }
                      }
                    ]
                  }
                },
                "label": {
                  "show": true
                },
                "extra": [
                  {
                    "fieldName": "quarter",
                    "displayName": "Quarter"
                  }
                ]
              }
            }
          },
          "position": {
            "x": 6,
            "y": 3,
            "width": 6,
            "height": 6
          }
        },
        {
          "widget": {
            "name": "069c486a",
            "queries": [
              {
                "name": "main_query",
                "query": {
                  "datasetName": "b506e8bb",
                  "disaggregated": false
                }
              }
            ],
            "spec": {
              "version": 1,
              "widgetType": "sankey",
              "encodings": {}
            }
          },
          "position": {
            "x": 0,
            "y": 9,
            "width": 6,
            "height": 6
          }
        }
      ],
      "pageType": "PAGE_TYPE_CANVAS",
      "layoutVersion": "GRID_V1"
    },
    {
      "name": "9cf505e0",
      "displayName": "Global Filters",
      "layout": [
        {
          "widget": {
            "name": "7580c024",
            "spec": {
              "version": 2,
              "widgetType": "filter-single-select",
              "encodings": {},
              "frame": {
                "showTitle": true
              }
            }
          },
          "position": {
            "x": 0,
            "y": 0,
            "width": 1,
            "height": 2
          }
        }
      ],
      "pageType": "PAGE_TYPE_GLOBAL_FILTERS",
      "layoutVersion": "GRID_V1"
    }
  ],
  "uiSettings": {
    "theme": {
      "canvasBackgroundColor": {
        "light": "#E7DEDB",
        "dark": "#DFCDCA"
      },
      "widgetBackgroundColor": {
        "light": "#FFFFFF",
        "dark": "#D38B7D"
      },
      "widgetBorderColor": {
        "light": "#FFFFFF",
        "dark": "#11171C"
      },
      "fontColor": {
        "light": "#11171C",
        "dark": "#742E2E"
      },
      "selectionColor": {
        "light": "#2272B4",
        "dark": "#8ACAFF"
      },
      "visualizationColors": [
        "#077A9D",
        "#FFAB00",
        "#00A972",
        "#FF3621",
        "#8BCAE7",
        "#AB4057",
        "#99DDB4",
        "#FCA4A1",
        "#919191",
        "#BF7080"
      ],
      "widgetHeaderAlignment": "LEFT",
      "fontFamily": "Georgia"
    },
    "applyModeEnabled": false
  }
}
